neuronlp/__init__.py
neuronlp-2024.12.12.dist-info/LICENSE
neuronlp-2024.12.12.dist-info/METADATA
neuronlp-2024.12.12.dist-info/WHEEL
neuronlp-2024.12.12.dist-info/top_level.txt
neuronlp-2024.12.12.dist-info/RECORD
