Metadata-Version: 2.1
Name: neuronlp
Version: 2024.12.12
Summary: NeuroNLP project
Home-page: https://github.com/deepmaterials/neuronlp
Author: Kamal Choudhary
Author-email: writetokamal.1989@gmail.com
Classifier: Development Status :: 3 - Alpha
Classifier: Intended Audience :: Developers
Classifier: Natural Language :: English
Classifier: Programming Language :: Python :: 3.9
Classifier: License :: OSI Approved :: MIT License
Classifier: Operating System :: OS Independent
Requires-Python: >=3.9
License-File: LICENSE
Requires-Dist: requests
